sweb/__init__.py
sweb/app.py
sweb/asset_manager.py
sweb/data_loader.py
sweb/style_processor.py
sweb/template_processor.py
sweb-0.7.dist-info/LICENSE
sweb-0.7.dist-info/METADATA
sweb-0.7.dist-info/WHEEL
sweb-0.7.dist-info/entry_points.txt
sweb-0.7.dist-info/top_level.txt
sweb-0.7.dist-info/RECORD
